JT_Gmail/__init__.py
JT_Gmail/gmail.py
JT_Gmail/util.py
JT_Gmail-0.0.24.data/data/requirements
JT_Gmail-0.0.24.dist-info/LICENSE
JT_Gmail-0.0.24.dist-info/METADATA
JT_Gmail-0.0.24.dist-info/WHEEL
JT_Gmail-0.0.24.dist-info/top_level.txt
JT_Gmail-0.0.24.dist-info/RECORD
