Metadata-Version: 2.1
Name: JT-Gmail
Version: 0.0.24
Summary: My Gmail API Wrapper
Home-page: https://github.com/Gothingbop/JT_Gmail
Author: Jacob Thompson
Author-email: Gothingbop@gmail.com
License: UNKNOWN
Platform: UNKNOWN
Classifier: Programming Language :: Python :: 3
Classifier: License :: OSI Approved :: MIT License
Classifier: Operating System :: OS Independent
Requires-Python: >=3
Requires-Dist: google-api-python-client
Requires-Dist: google-auth-httplib2
Requires-Dist: google-auth-oauthlib
